influx_logs/__init__.py
influx_logs/actions.py
influx_logs/apps.py
influx_logs/connexion.py
influx_logs/settings.py
django_influx_logs-0.0.5.dist-info/LICENSE
django_influx_logs-0.0.5.dist-info/METADATA
django_influx_logs-0.0.5.dist-info/WHEEL
django_influx_logs-0.0.5.dist-info/top_level.txt
django_influx_logs-0.0.5.dist-info/RECORD
