Metadata-Version: 2.1
Name: django-influx-logs
Version: 0.0.5
Summary: Django Influx Logs: put your application logs into InfluxDB.
Home-page: https://github.com/lazybird/django-influx-logs/
Author: lazybird
License: MIT License
Platform: UNKNOWN
License-File: LICENSE
Requires-Dist: influxdb
